geonames_client/__init__.py
geonames_client/__main__.py
geonames_client/client.py
geonames_client/util.py
geonames_client-0.0.2.dist-info/METADATA
geonames_client-0.0.2.dist-info/WHEEL
geonames_client-0.0.2.dist-info/entry_points.txt
geonames_client-0.0.2.dist-info/top_level.txt
geonames_client-0.0.2.dist-info/RECORD
