Metadata-Version: 2.1
Name: geonames-client
Version: 0.0.2
Summary: A module for interfacing with the geonames.org API.
Author: Yora Technologies
Author-email: info@yora.tech
License: UNKNOWN
Platform: UNKNOWN
